tailless/__init__.py
tailless-0.1.0.dist-info/LICENSE
tailless-0.1.0.dist-info/METADATA
tailless-0.1.0.dist-info/WHEEL
tailless-0.1.0.dist-info/RECORD
