Metadata-Version: 2.1
Name: tailless
Version: 0.1.0
Summary: A hybrid of tail and less
License: MIT
Author: Will McGugan
Author-email: will@textualize.io
Requires-Python: >=3.8,<4.0
Classifier: License :: OSI Approved :: MIT License
Classifier: Programming Language :: Python :: 3
Classifier: Programming Language :: Python :: 3.8
Classifier: Programming Language :: Python :: 3.9
Classifier: Programming Language :: Python :: 3.10
Classifier: Programming Language :: Python :: 3.11
Requires-Dist: textual (>=0.47.1,<0.48.0)
